uptainer/__init__.py
uptainer/cli.py
uptainer/config.py
uptainer/git.py
uptainer/loader.py
uptainer/typer.py
uptainer/uptainer.py
uptainer/providers/__init__.py
uptainer/providers/baseprovider.py
uptainer/providers/dockerhub.py
uptainer/providers/github.py
uptainer-0.2.3.dist-info/AUTHORS.rst
uptainer-0.2.3.dist-info/LICENSE.txt
uptainer-0.2.3.dist-info/METADATA
uptainer-0.2.3.dist-info/WHEEL
uptainer-0.2.3.dist-info/entry_points.txt
uptainer-0.2.3.dist-info/top_level.txt
uptainer-0.2.3.dist-info/RECORD
