Metadata-Version: 2.2
Name: uptainer
Version: 0.2.3
Summary: Uptainer is a Python CLI that automates tool updates, ensuring consistency and reliability in your GitOps-driven infrastructure.
Author-email: Alessandro Sbarbati <122787746+asbarbati@users.noreply.github.com>
Maintainer-email: Alessandro Sbarbati <122787746+asbarbati@users.noreply.github.com>
License: GNU General Public License v3
Project-URL: homepage, https://github.com/asbarbati/uptainer
Project-URL: docs, https://uptainer.readthedocs.io
Project-URL: source, https://github.com/asbarbati/uptainer/
Project-URL: bugs, https://github.com/asbarbati/uptainer/issues
Project-URL: changelog, https://github.com/asbarbati/uptainer/blob/master/changelog.md
Classifier: Development Status :: 3 - Alpha
Classifier: Environment :: Console
Classifier: Intended Audience :: Developers
Classifier: Intended Audience :: System Administrators
Classifier: License :: OSI Approved :: GNU General Public License v3 (GPLv3)
License-File: LICENSE.txt
License-File: AUTHORS.rst
Requires-Dist: GitPython
Requires-Dist: pre_commit
Requires-Dist: python-box
Requires-Dist: PyYAML
Requires-Dist: requests
Requires-Dist: structlog
Requires-Dist: typer
Requires-Dist: types-PyYAML
Requires-Dist: types-requests
Provides-Extra: dev
Requires-Dist: coverage; extra == "dev"
Requires-Dist: mypy; extra == "dev"
Requires-Dist: pytest; extra == "dev"
Requires-Dist: ruff; extra == "dev"
